midea_python_client/__init__.py
midea_python_client/midea_client.py
midea_python_client/midea_databody_dehumi_query.py
midea_python_client/midea_databody_dehumi_request.py
midea_python_client/midea_databody_dehumi_response.py
midea_python_client/midea_dehumidification_device.py
midea_python_client/midea_fcCon.py
midea_python_client/midea_security.py
midea_python_client-1.0.2.dist-info/AUTHORS
midea_python_client-1.0.2.dist-info/LICENSE
midea_python_client-1.0.2.dist-info/METADATA
midea_python_client-1.0.2.dist-info/WHEEL
midea_python_client-1.0.2.dist-info/top_level.txt
midea_python_client-1.0.2.dist-info/RECORD
