Metadata-Version: 2.1
Name: midea-python-client
Version: 1.0.2
Summary: Client-side Python library for EVA II PRO WiFi Smart Dehumidifier appliance by Midea/Inventor.
Home-page: https://github.com/barban-dev/midea_inventor_dehumidifier
Author: Dell'Oro Giulio
Author-email: dellorogiulio@gmail.com
Classifier: Development Status :: 5 - Production/Stable
Classifier: Programming Language :: Python :: 2.7
Classifier: License :: OSI Approved :: GNU General Public License v3 (GPLv3)
Classifier: Operating System :: OS Independent
Classifier: Programming Language :: Python
Classifier: Programming Language :: Python :: 2.7
Classifier: Programming Language :: Python :: 3.4
Classifier: Programming Language :: Python :: 3.5
Classifier: Programming Language :: Python :: 3.6
Classifier: Topic :: Software Development :: Libraries :: Python Modules
License-File: LICENSE
License-File: AUTHORS
Requires-Dist: requests (>=2.16.0)
Requires-Dist: pycryptodome (>=3.6.6)
